service_markets/__init__.py
service_markets/api/__init__.py
service_markets/api/api_model.py
service_markets/api/main.py
service_markets/api/routers/__init__.py
service_markets/api/routers/services.py
service_markets/api/routers/users.py
service_markets/api/utils.py
service_markets/core/__init__.py
service_markets/core/constants.py
service_markets/core/heimdall.py
service_markets/core/model.py
service_markets/core/request_network.py
service_markets/core/session.py
service_markets/local_listener.py
service_markets/py.typed
service_markets-0.3.17.dist-info/LICENSE
service_markets-0.3.17.dist-info/METADATA
service_markets-0.3.17.dist-info/WHEEL
service_markets-0.3.17.dist-info/RECORD
