Metadata-Version: 2.1
Name: service-markets
Version: 0.3.17
Summary: Software-as-a-Service (SaaS) Marketplace with cryptocurrency payments
License: AGPL-3.0
Author: Mike Hukiewitz
Author-email: mike.hukiewitz@robotter.ai
Requires-Python: >=3.9,<4.0
Classifier: License :: OSI Approved :: GNU Affero General Public License v3
Classifier: Programming Language :: Python :: 3
Classifier: Programming Language :: Python :: 3.9
Classifier: Programming Language :: Python :: 3.10
Classifier: Programming Language :: Python :: 3.11
Requires-Dist: PyNaCl (>=1.5.0,<2.0.0)
Requires-Dist: aars (>=0.7.2,<0.8.0)
Requires-Dist: aiohttp (>=3.8.4,<4.0.0)
Requires-Dist: aleph-sdk-python (>=0.6.0,<0.7.0)
Requires-Dist: base58 (>=2.1.1,<3.0.0)
Requires-Dist: fastapi (>=0.95.1,<0.96.0)
Requires-Dist: fastapi-walletauth (>=0.1.8,<0.2.0)
Requires-Dist: pydantic (>=1.10.8,<2.0.0)
Requires-Dist: python-multipart (>=0.0.6,<0.0.7)
Requires-Dist: requests (>=2.30.0,<3.0.0)
Requires-Dist: semver (>=3.0.0,<4.0.0)
